{
  "Version": "2012-10-17",
  "Statement": [
    {
      "Sid": "Stmt1486409827000",
      "Effect": "Allow",
      "Action": [
        "polly:SynthesizeSpeech"
      ],
      "Resource": [
        "*"
      ]
    },
    {
      "Sid": "Stmt1486410006000",
      "Effect": "Allow",
      "Action": [
        "s3:PutObject",
        "s3:PutObjectAcl"
      ],
      "Resource": [
        "arn:aws:s3:::getaves.com/*"
      ]
    },
    {
      "Sid": "Stmt1486410260000",
      "Effect": "Allow",
      "Action": [
        "dynamodb:PutItem"
      ],
      "Resource": [
        "arn:aws:dynamodb:eu-west-1:353598037903:table/mapping"
      ]
    }
  ]
}